faag/__init__.py
faag/constants/__init__.py
faag/constants/app_types.py
faag/constants/constants.py
faag/core/__init__.py
faag/core/app_generator.py
faag/core/feature_generator.py
faag/faag.py
faag/templates/base/__init__.jinja
faag/templates/base/fast__init__.jinja
faag/templates/base/flask__init__.jinja
faag/templates/config/config.jinja
faag/templates/config/config__init__.jinja
faag/templates/config/constants.jinja
faag/templates/connection/connection__init__.jinja
faag/templates/controller/controller__init__.jinja
faag/templates/controller/fast_controller.jinja
faag/templates/controller/fast_controller__init__.jinja
faag/templates/controller/flask_controller.jinja
faag/templates/controller/flask_controller__init__.jinja
faag/templates/controller/sample_controller.jinja
faag/templates/dao/dao__init__.jinja
faag/templates/dao/sample_dao.jinja
faag/templates/gitignore.jinja
faag/templates/model/model__init__.jinja
faag/templates/model/sample_model.jinja
faag/templates/schemas/response/common_response_schema.jinja
faag/templates/schemas/response/user_response_schema.jinja
faag/templates/schemas/schemas__init__.jinja
faag/templates/service/sample_service.jinja
faag/templates/service/service__init__.jinja
faag/templates/utils/logger.jinja
faag/templates/utils/utils__init__.jinja
faag/utils/__init__.py
faag/utils/faag_utils.py
faag/utils/templates_loader.py
faag-0.0.1.dev0.dist-info/LICENSE
faag-0.0.1.dev0.dist-info/WHEEL
faag-0.0.1.dev0.dist-info/entry_points.txt
faag-0.0.1.dev0.dist-info/METADATA
faag-0.0.1.dev0.dist-info/RECORD
